LICENSE
MANIFEST.in
README.rst
setup.py
licenses/burrito.txt
licenses/greengenes.txt
licenses/scikit-bio.txt
qiime_default_reference/__init__.py
qiime_default_reference.egg-info/PKG-INFO
qiime_default_reference.egg-info/SOURCES.txt
qiime_default_reference.egg-info/dependency_links.txt
qiime_default_reference.egg-info/requires.txt
qiime_default_reference.egg-info/top_level.txt
qiime_default_reference/gg_13_8_otus/__init__.py
qiime_default_reference/gg_13_8_otus/rep_set/97_otus.fasta.gz
qiime_default_reference/gg_13_8_otus/rep_set_aligned/85_otus.pynast.fasta.gz
qiime_default_reference/gg_13_8_otus/taxonomy/97_otu_taxonomy.txt.gz
qiime_default_reference/gg_13_8_otus/trees/97_otus.tree.gz
qiime_default_reference/tests/__init__.py
qiime_default_reference/tests/test_init.py