Metadata-Version: 1.1
Name: qiime-default-reference
Version: 0.1.2
Summary: Default reference data files for use with QIIME.
Home-page: http://www.qiime.org
Author: QIIME development team
Author-email: qiime.help@gmail.com
License: CC BY-SA 3.0
Platform: UNKNOWN
Classifier: Development Status :: 3 - Alpha
Classifier: Topic :: Scientific/Engineering :: Bio-Informatics
Classifier: Programming Language :: Python
Classifier: Programming Language :: Python :: 2
Classifier: Programming Language :: Python :: 2.7
Classifier: Operating System :: Unix
Classifier: Operating System :: POSIX
Classifier: Operating System :: MacOS :: MacOS X
